{
  "status": "passed",
  "rootPageId": "2221670415",
  "checkedPages": 12,
  "checks": [
    {
      "treePath": ["Sonic Data Lineage", "AI Retrieval Artifacts"],
      "id": "2283831324",
      "version": 8,
      "labels": [
        "data-lineage",
        "lineage-catalog",
        "ai-retrieval-artifacts",
        "human-lineage-catalog",
        "rovo-ai-retrieval",
        "ai-retrieval-artifact",
        "lineage-product-catalog",
        "reviewed-slice"
      ],
      "snippetsChecked": []
    },
    {
      "treePath": ["Sonic Data Lineage", "Data Product Catalog"],
      "id": "2282651652",
      "version": 10,
      "labels": [
        "human-lineage-catalog",
        "lineage-pilot",
        "reviewed-pilot",
        "lineage-product-catalog",
        "reviewed-slice"
      ],
      "snippetsChecked": []
    },
    {
      "treePath": [
        "Sonic Data Lineage",
        "AI Retrieval Artifacts",
        "MDP AWS Rovo Lineage Context 001"
      ],
      "id": "2324987907",
      "version": 2,
      "labels": [
        "human-lineage-catalog",
        "rovo-ai-retrieval",
        "ai-retrieval-artifact",
        "aws-lineage",
        "mdp"
      ],
      "snippetsChecked": ["Plain-English Summary", "Technical Evidence"]
    },
    {
      "treePath": [
        "Sonic Data Lineage",
        "AI Retrieval Artifacts",
        "MDP AWS Rovo Object Locator 001"
      ],
      "id": "2325020673",
      "version": 2,
      "labels": [
        "human-lineage-catalog",
        "rovo-ai-retrieval",
        "ai-retrieval-artifact",
        "aws-lineage",
        "mdp"
      ],
      "snippetsChecked": ["Plain-English Summary", "Technical Evidence"]
    },
    {
      "treePath": [
        "Sonic Data Lineage",
        "AI Retrieval Artifacts",
        "MDP AWS Rovo Object Summary Context 001"
      ],
      "id": "2325053441",
      "version": 2,
      "labels": [
        "human-lineage-catalog",
        "rovo-ai-retrieval",
        "ai-retrieval-artifact",
        "aws-lineage",
        "mdp"
      ],
      "snippetsChecked": ["Plain-English Summary", "Technical Evidence"]
    },
    {
      "treePath": ["Sonic Data Lineage", "AI Retrieval Artifacts", "MDP AWS Rovo Start Here"],
      "id": "2325086209",
      "version": 2,
      "labels": [
        "human-lineage-catalog",
        "rovo-ai-retrieval",
        "ai-retrieval-artifact",
        "aws-lineage",
        "mdp"
      ],
      "snippetsChecked": ["Plain-English Summary", "Technical Evidence"]
    },
    {
      "treePath": ["Sonic Data Lineage", "Data Product Catalog", "MDP AWS Lineage Context"],
      "id": "2325118977",
      "version": 2,
      "labels": ["human-lineage-catalog", "lineage-product-catalog", "aws-lineage", "mdp"],
      "snippetsChecked": ["Plain-English Summary", "Technical Evidence"]
    },
    {
      "treePath": [
        "Sonic Data Lineage",
        "Data Product Catalog",
        "MDP AWS Lineage Context",
        "AWS Accounts And Services"
      ],
      "id": "2325151745",
      "version": 2,
      "labels": ["human-lineage-catalog", "lineage-product-catalog", "aws-lineage", "mdp"],
      "snippetsChecked": ["Plain-English Summary", "Technical Evidence"]
    },
    {
      "treePath": [
        "Sonic Data Lineage",
        "Data Product Catalog",
        "MDP AWS Lineage Context",
        "Data Team Feed Summary"
      ],
      "id": "2324561925",
      "version": 2,
      "labels": ["human-lineage-catalog", "lineage-product-catalog", "aws-lineage", "mdp"],
      "snippetsChecked": ["Plain-English Summary", "Technical Evidence"]
    },
    {
      "treePath": [
        "Sonic Data Lineage",
        "Data Product Catalog",
        "MDP AWS Lineage Context",
        "Known Gaps And Ownership"
      ],
      "id": "2325217281",
      "version": 2,
      "labels": ["human-lineage-catalog", "lineage-product-catalog", "aws-lineage", "mdp"],
      "snippetsChecked": ["Plain-English Summary", "Technical Evidence"]
    },
    {
      "treePath": [
        "Sonic Data Lineage",
        "Data Product Catalog",
        "MDP AWS Lineage Context",
        "S3 Glue Athena Lineage"
      ],
      "id": "2324594691",
      "version": 2,
      "labels": ["human-lineage-catalog", "lineage-product-catalog", "aws-lineage", "mdp"],
      "snippetsChecked": ["Plain-English Summary", "Technical Evidence"]
    },
    {
      "treePath": [
        "Sonic Data Lineage",
        "Data Product Catalog",
        "MDP AWS Lineage Context",
        "Technical Evidence And Readbacks"
      ],
      "id": "2324496386",
      "version": 2,
      "labels": ["human-lineage-catalog", "lineage-product-catalog", "aws-lineage", "mdp"],
      "snippetsChecked": ["Plain-English Summary", "Technical Evidence"]
    }
  ],
  "failures": []
}
